odoo/addons/ssi_lead_project/README.rst
odoo/addons/ssi_lead_project/__init__.py
odoo/addons/ssi_lead_project/__manifest__.py
odoo/addons/ssi_lead_project/i18n/ssi_lead_project.pot
odoo/addons/ssi_lead_project/models/__init__.py
odoo/addons/ssi_lead_project/models/crm_lead.py
odoo/addons/ssi_lead_project/static/description/icon.png
odoo14_addon_ssi_lead_project-14.0.1.1.0.dist-info/METADATA
odoo14_addon_ssi_lead_project-14.0.1.1.0.dist-info/WHEEL
odoo14_addon_ssi_lead_project-14.0.1.1.0.dist-info/top_level.txt
odoo14_addon_ssi_lead_project-14.0.1.1.0.dist-info/RECORD
